[
  {
    "Type": "DataTable",
    "Name": "DT_Message_Template_Mail",
    "Class": "UScriptClass'DataTable'",
    "Properties": {
      "RowStruct": {
        "ObjectName": "ScriptStruct'MessageTemplateMailTableRow'",
        "ObjectPath": "/Script/Overprime"
      }
    },
    "Rows": {
      "2001": {
        "SenderNameKey": "UI.MsgTemplate_SenderName_System",
        "TitleID": 200101,
        "ContentsID": 200102,
        "Importance": true,
        "ExpireHour": 999999,
        "MailLinkID": 5
      },
      "2002": {
        "SenderNameKey": "UI.MsgTemplate_SenderName_System",
        "TitleID": 200201,
        "ContentsID": 200202,
        "Importance": true,
        "ExpireHour": 999999,
        "MailLinkID": 0
      },
      "2003": {
        "SenderNameKey": "UI.MsgTemplate_SenderName_System",
        "TitleID": 200301,
        "ContentsID": 200302,
        "Importance": true,
        "ExpireHour": 999999,
        "MailLinkID": 0
      },
      "2004": {
        "SenderNameKey": "UI.MsgTemplate_SenderName_System",
        "TitleID": 200401,
        "ContentsID": 200402,
        "Importance": true,
        "ExpireHour": 168,
        "MailLinkID": 4
      },
      "2005": {
        "SenderNameKey": "UI.MsgTemplate_SenderName_System",
        "TitleID": 200501,
        "ContentsID": 200502,
        "Importance": false,
        "ExpireHour": 168,
        "MailLinkID": 0
      },
      "2006": {
        "SenderNameKey": "UI.MsgTemplate_SenderName_System",
        "TitleID": 200601,
        "ContentsID": 200602,
        "Importance": true,
        "ExpireHour": 999999,
        "MailLinkID": 6
      },
      "2007": {
        "SenderNameKey": "UI.MsgTemplate_SenderName_System",
        "TitleID": 200701,
        "ContentsID": 200702,
        "Importance": true,
        "ExpireHour": 999999,
        "MailLinkID": 0
      },
      "2008": {
        "SenderNameKey": "UI.MsgTemplate_SenderName_System",
        "TitleID": 200801,
        "ContentsID": 200802,
        "Importance": true,
        "ExpireHour": 999999,
        "MailLinkID": 0
      },
      "2009": {
        "SenderNameKey": "UI.MsgTemplate_SenderName_System",
        "TitleID": 200901,
        "ContentsID": 200902,
        "Importance": true,
        "ExpireHour": 999999,
        "MailLinkID": 0
      },
      "2010": {
        "SenderNameKey": "UI.MsgTemplate_SenderName_System",
        "TitleID": 201001,
        "ContentsID": 201002,
        "Importance": true,
        "ExpireHour": 999999,
        "MailLinkID": 0
      },
      "2011": {
        "SenderNameKey": "UI.MsgTemplate_SenderName_System",
        "TitleID": 201101,
        "ContentsID": 201102,
        "Importance": true,
        "ExpireHour": 999999,
        "MailLinkID": 7
      },
      "2012": {
        "SenderNameKey": "UI.MsgTemplate_SenderName_System",
        "TitleID": 201201,
        "ContentsID": 201202,
        "Importance": true,
        "ExpireHour": 999999,
        "MailLinkID": 7
      },
      "2013": {
        "SenderNameKey": "UI.MsgTemplate_SenderName_System",
        "TitleID": 201301,
        "ContentsID": 201302,
        "Importance": true,
        "ExpireHour": 999999,
        "MailLinkID": 7
      },
      "2014": {
        "SenderNameKey": "UI.MsgTemplate_SenderName_System",
        "TitleID": 201401,
        "ContentsID": 201402,
        "Importance": true,
        "ExpireHour": 999999,
        "MailLinkID": 7
      },
      "2015": {
        "SenderNameKey": "UI.MsgTemplate_SenderName_System",
        "TitleID": 201501,
        "ContentsID": 201502,
        "Importance": true,
        "ExpireHour": 999999,
        "MailLinkID": 6
      },
      "2016": {
        "SenderNameKey": "UI.MsgTemplate_SenderName_System",
        "TitleID": 201601,
        "ContentsID": 201602,
        "Importance": true,
        "ExpireHour": 999999,
        "MailLinkID": 6
      },
      "2017": {
        "SenderNameKey": "UI.MsgTemplate_SenderName_System",
        "TitleID": 201701,
        "ContentsID": 201702,
        "Importance": true,
        "ExpireHour": 999999,
        "MailLinkID": 6
      },
      "2018": {
        "SenderNameKey": "UI.MsgTemplate_SenderName_System",
        "TitleID": 201801,
        "ContentsID": 201802,
        "Importance": true,
        "ExpireHour": 999999,
        "MailLinkID": 0
      },
      "2019": {
        "SenderNameKey": "UI.MsgTemplate_SenderName_System",
        "TitleID": 201901,
        "ContentsID": 201902,
        "Importance": true,
        "ExpireHour": 999999,
        "MailLinkID": 0
      },
      "2020": {
        "SenderNameKey": "UI.MsgTemplate_SenderName_System",
        "TitleID": 202001,
        "ContentsID": 202002,
        "Importance": true,
        "ExpireHour": 999999,
        "MailLinkID": 0
      },
      "2021": {
        "SenderNameKey": "UI.MsgTemplate_SenderName_System",
        "TitleID": 202101,
        "ContentsID": 202102,
        "Importance": true,
        "ExpireHour": 999999,
        "MailLinkID": 0
      },
      "2022": {
        "SenderNameKey": "UI.MsgTemplate_SenderName_System",
        "TitleID": 202201,
        "ContentsID": 202202,
        "Importance": true,
        "ExpireHour": 999999,
        "MailLinkID": 0
      },
      "2023": {
        "SenderNameKey": "UI.MsgTemplate_SenderName_System",
        "TitleID": 202301,
        "ContentsID": 202302,
        "Importance": true,
        "ExpireHour": 999999,
        "MailLinkID": 6
      },
      "2024": {
        "SenderNameKey": "UI.MsgTemplate_SenderName_System",
        "TitleID": 202401,
        "ContentsID": 202402,
        "Importance": true,
        "ExpireHour": 999999,
        "MailLinkID": 0
      },
      "2025": {
        "SenderNameKey": "UI.MsgTemplate_SenderName_System",
        "TitleID": 202501,
        "ContentsID": 202502,
        "Importance": true,
        "ExpireHour": 999999,
        "MailLinkID": 4
      },
      "2026": {
        "SenderNameKey": "UI.MsgTemplate_SenderName_System",
        "TitleID": 100801,
        "ContentsID": 100802,
        "Importance": true,
        "ExpireHour": 999999,
        "MailLinkID": 4
      },
      "2027": {
        "SenderNameKey": "UI.MsgTemplate_SenderName_System",
        "TitleID": 202701,
        "ContentsID": 202702,
        "Importance": true,
        "ExpireHour": 2162,
        "MailLinkID": 6
      },
      "2028": {
        "SenderNameKey": "UI.MsgTemplate_SenderName_System",
        "TitleID": 202801,
        "ContentsID": 202802,
        "Importance": true,
        "ExpireHour": 999999,
        "MailLinkID": 6
      },
      "2029": {
        "SenderNameKey": "UI.MsgTemplate_SenderName_System",
        "TitleID": 202901,
        "ContentsID": 202902,
        "Importance": true,
        "ExpireHour": 999999,
        "MailLinkID": 0
      },
      "2030": {
        "SenderNameKey": "UI.MsgTemplate_SenderName_System",
        "TitleID": 203001,
        "ContentsID": 203002,
        "Importance": true,
        "ExpireHour": 999999,
        "MailLinkID": 2
      }
    }
  }
]